geo_tools/__init__.py
geo_tools/command_line.py
geo_tools/errors.py
geo_tools/manager.py
geo_tools/point.py
geo_tools/scripts.py
spatial_point_manager-0.0.1.dist-info/METADATA
spatial_point_manager-0.0.1.dist-info/WHEEL
spatial_point_manager-0.0.1.dist-info/entry_points.txt
spatial_point_manager-0.0.1.dist-info/top_level.txt
spatial_point_manager-0.0.1.dist-info/RECORD
